{
  "components": {
    "blake3": [
      "./components/blake3/blake3.yakka"
    ],
    "circular_blueprints": [
      "./test/circular_blueprints.yakka"
    ],
    "clang": [
      "./tools/toolchains/clang/clang.yakka"
    ],
    "cmake": [
      "./tools/cmake.yakka"
    ],
    "cpp-httplib": [
      "./components/cpp-httplib/cpp-httplib.yakka"
    ],
    "cpp-semver": [
      "./components/cpp-semver/cpp-semver.yakka"
    ],
    "cpp-subprocess": [
      "./components/cpp-subprocess/cpp-subprocess.yakka"
    ],
    "cryptopp": [
      "./components/cryptopp/cryptopp.yakka"
    ],
    "cxxopts": [
      "./components/cxxopts/cxxopts.yakka"
    ],
    "fmt": [
      "./components/fmtlib/fmt.yakka"
    ],
    "ftxui": [
      "./components/ftxui/ftxui.yakka"
    ],
    "gcc": [
      "./tools/toolchains/gcc/gcc.yakka"
    ],
    "glob": [
      "./components/glob/glob.yakka"
    ],
    "googletest": [
      "./components/googletest/googletest.yakka"
    ],
    "http-client-example": [
      "./components/cpp-httplib/http-client-example.yakka"
    ],
    "indicators": [
      "./components/indicators/indicators.yakka"
    ],
    "inja": [
      "./components/inja/inja.yakka"
    ],
    "jinja2cpp": [
      "./components/jinja2cpp/jinja2cpp.yakka"
    ],
    "json": [
      "./components/json/json.yakka"
    ],
    "json-schema-validator": [
      "./components/json-schema-validator/json-schema-validator.yakka"
    ],
    "msvc": [
      "./tools/toolchains/msvc/msvc.yakka"
    ],
    "perf_test": [
      "./perf_test/perf_test.yakka"
    ],
    "pugixml": [
      "./components/pugixml/pugixml.yakka"
    ],
    "rapidyaml": [
      "./components/rapidyaml/rapidyaml.yakka"
    ],
    "semver": [
      "./components/semver/semver.yakka"
    ],
    "spdlog": [
      "./components/spdlog/spdlog.yakka"
    ],
    "taskflow": [
      "./components/taskflow/taskflow.yakka"
    ],
    "toml++": [
      "./components/tomlplusplus/toml++.yakka"
    ],
    "unit_tests": [
      "./test/unit_tests.yakka"
    ],
    "xcode": [
      "./tools/toolchains/xcode/xcode.yakka"
    ],
    "yakka": [
      "./yakka/yakka.yakka"
    ],
    "yakka-config": [
      "./yakka-config/yakka-config.yakka"
    ],
    "yakka_cli": [
      "./yakka/yakka_cli.yakka"
    ],
    "yakka_test": [
      "./yakka/yakka_test.yakka"
    ],
    "yaml-cpp": [
      "./components/yaml-cpp/yaml-cpp.yakka"
    ],
    "yinja": [
      "./yinja/yinja.yakka"
    ]
  },
  "features": null
}